lead_md.py
lead_md-1.1.2.dist-info/LICENCE
lead_md-1.1.2.dist-info/METADATA
lead_md-1.1.2.dist-info/WHEEL
lead_md-1.1.2.dist-info/top_level.txt
lead_md-1.1.2.dist-info/RECORD
