Metadata-Version: 2.2
Name: lead_md
Version: 1.1.2
Summary: Renders markdown to the terminal using producesyntaxed
Author-email: Pittab <Pittab.0001@gmail.com>
License:            DO WHAT THE FUCK YOU WANT TO PUBLIC LICENSE
License-File: LICENCE
Requires-Dist: producesyntaxed
